mistat/__init__.py
mistat/bayes.py
mistat/data.py
mistat/ecdf.py
mistat/patches.py
mistat/randomizationTest.py
mistat/reliability.py
mistat/runsTest.py
mistat/stem_leaf.py
mistat/version.py
mistat/acceptanceSampling/__init__.py
mistat/acceptanceSampling/bandit.py
mistat/acceptanceSampling/distributions.py
mistat/acceptanceSampling/generic.py
mistat/acceptanceSampling/oc.py
mistat/acceptanceSampling/dodge/__init__.py
mistat/acceptanceSampling/dodge/dodge_base.py
mistat/acceptanceSampling/dodge/dodge_chain.py
mistat/acceptanceSampling/dodge/dodge_curtailed.py
mistat/acceptanceSampling/dodge/dodge_double.py
mistat/acceptanceSampling/dodge/dodge_other.py
mistat/acceptanceSampling/dodge/dodge_sequential.py
mistat/acceptanceSampling/dodge/dodge_single.py
mistat/acceptanceSampling/dodge/tests/__init__.py
mistat/acceptanceSampling/dodge/tests/test_dodge.py
mistat/acceptanceSampling/tests/__init__.py
mistat/acceptanceSampling/tests/test_bandit.py
mistat/acceptanceSampling/tests/test_distributions.py
mistat/acceptanceSampling/tests/test_generic.py
mistat/acceptanceSampling/tests/test_oc.py
mistat/csvFiles/ABC.csv.gz
mistat/csvFiles/ABC2.csv.gz
mistat/csvFiles/AIRCRAFTINCIDENTS.csv.gz
mistat/csvFiles/AIRLINE_SURVEY.csv.gz
mistat/csvFiles/ALMPIN.csv.gz
mistat/csvFiles/ALMPIN2.csv.gz
mistat/csvFiles/BLEMISHES.csv.gz
mistat/csvFiles/CAR.csv.gz
mistat/csvFiles/CAR_EXAMPLE.csv.gz
mistat/csvFiles/CEMENT.csv.gz
mistat/csvFiles/COAL.csv.gz
mistat/csvFiles/COMPURESP.csv.gz
mistat/csvFiles/CONTACTLEN.csv.gz
mistat/csvFiles/CUSTOMDESIGN_169.csv.gz
mistat/csvFiles/CUSTOMDESIGN_35.csv.gz
mistat/csvFiles/CUSTOMDESIGN_80.csv.gz
mistat/csvFiles/CYCLT.csv.gz
mistat/csvFiles/DISS.csv.gz
mistat/csvFiles/DISSOLUTION.csv.gz
mistat/csvFiles/DISTILLATION-TOWER.csv.gz
mistat/csvFiles/DOJO1935.csv.gz
mistat/csvFiles/DOW1941.csv.gz
mistat/csvFiles/DOW1941_DATE.csv.gz
mistat/csvFiles/ELECFAIL.csv.gz
mistat/csvFiles/ELECINDX.csv.gz
mistat/csvFiles/ETCHRATE.csv.gz
mistat/csvFiles/ETCHRATETWO.csv.gz
mistat-0.1.16.dist-info/LICENSE
mistat-0.1.16.dist-info/METADATA
mistat-0.1.16.dist-info/WHEEL
mistat-0.1.16.dist-info/top_level.txt
mistat-0.1.16.dist-info/RECORD
