Metadata-Version: 2.1
Name: mistat
Version: 0.1.16
Summary: Utility functions for 'Modern Industrial Statistics'
Home-page: https://github.com/gedeck/mistat
Author: Peter Gedeck
Author-email: mail@petergedeck.com
Classifier: Programming Language :: Python :: 3
Classifier: Programming Language :: Python :: 3.8
Classifier: Programming Language :: Python :: 3.9
Classifier: Programming Language :: Python :: 3.10
Classifier: Programming Language :: Python :: 3.11
Classifier: Programming Language :: Python :: 3.12
Classifier: License :: OSI Approved :: MIT License
Classifier: Operating System :: OS Independent
License-File: LICENSE
Requires-Dist: pyDOE3
Requires-Dist: diversipy
Requires-Dist: pingouin
